geostream/__init__.py
geostream/wfs.py
geostream-0.0.1.dist-info/LICENSE
geostream-0.0.1.dist-info/METADATA
geostream-0.0.1.dist-info/WHEEL
geostream-0.0.1.dist-info/top_level.txt
geostream-0.0.1.dist-info/RECORD
