Metadata-Version: 2.1
Name: geostream
Version: 0.0.1
Summary: Python tool to interact with OGC APIs with ease.
Home-page: https://github.com/geostream-org/geostream
Author: Henrikki Tenkanen
Author-email: henrikki.tenkanen@aalto.fi
License: MIT
Project-URL: Documentation, https://github.com/geostream-org/geostream
Project-URL: Change Log, https://github.com/geostream-org/geostream/CHANGELOG.md
Project-URL: Bug Tracker, https://github.com/geostream-org/geostream/issues
Classifier: Programming Language :: Python :: 3
Classifier: License :: OSI Approved :: MIT License
Classifier: Operating System :: OS Independent
Requires-Python: >=3.7
License-File: LICENSE
Requires-Dist: geopandas
Requires-Dist: pandas
Requires-Dist: osmnx
Requires-Dist: owslib
Requires-Dist: requests
